data_pipeline/data_process/data_convert/data_convert
data_pipeline/data_process/data_convert/data_convert.py
data_pipeline/data_process/utils/data_check.py
data_pipeline/data_process/utils/data_load.py
data_pipeline/data_process/utils/data_read.py
data_pipeline/data_process/utils/legacy_episode_state.py
data_pipeline/data_process/utils/message_convert.py
data_pipeline/data_process/utils/output_dataset.py
data_pipeline/data_process/utils/topic_mapping.py
data_pipeline/py_api/api_utils.py
data_pipeline/py_api/raw_api.py
data_pipeline/py_api/utils.py
tairos_data_convert-1.0.10.dist-info/WHEEL
tairos_data_convert-1.0.10.dist-info/METADATA
tairos_data_convert-1.0.10.dist-info/RECORD
