Metadata-Version: 2.1
Name: tairos-data-convert
Requires-Dist: mcap
Requires-Dist: mcap-ros1-support
Version: 1.0.10
